README.rst
setup.py
gdrv/__init__.py
gdrv/__main__.py
gdrv/ftp.py
gdrv/global_mod.py
gdrv/main.py
gdrv.egg-info/PKG-INFO
gdrv.egg-info/SOURCES.txt
gdrv.egg-info/dependency_links.txt
gdrv.egg-info/entry_points.txt
gdrv.egg-info/not-zip-safe
gdrv.egg-info/requires.txt
gdrv.egg-info/top_level.txt
gdrv/commands/__init__.py
gdrv/commands/command_base.py
gdrv/commands/command_init.py
gdrv/commands/command_list.py
gdrv/commands/command_mkdir.py
gdrv/commands/command_pull.py
gdrv/commands/command_push.py
gdrv/commands/command_search.py
gdrv/commands/command_share.py
gdrv/commands/command_trash.py
gdrv/commands/command_url.py