Metadata-Version: 1.0
Name: gdrv
Version: 0.2.1
Summary: Another google drive command line interface program
Home-page: https://github.com/yumaokao/gdrv
Author: yumaokao
Author-email: ymkq9h@gmail.com
License: MIT
Platform: UNKNOWN
